pyhanko_eoi/__init__.py
pyhanko_eoi/cli.py
pyhanko_eoi/eoi.py
pyhanko_eoi/py.typed
pyhanko_eoi_plugin-0.1.1.dist-info/LICENSE
pyhanko_eoi_plugin-0.1.1.dist-info/METADATA
pyhanko_eoi_plugin-0.1.1.dist-info/WHEEL
pyhanko_eoi_plugin-0.1.1.dist-info/entry_points.txt
pyhanko_eoi_plugin-0.1.1.dist-info/top_level.txt
pyhanko_eoi_plugin-0.1.1.dist-info/RECORD
