Metadata-Version: 2.1
Name: pyhanko-eoi-plugin
Version: 0.1.1
Summary: pyHanko plugin for Slovenian eOI cards
Author-email: Miha Šetina <miha.setina@gmail.com>
Maintainer-email: Miha Šetina <miha.setina@gmail.com>
License: MIT
Project-URL: Homepage, https://github.com/msetina/pyhanko-eoi-plugin
Project-URL: Source Code, https://github.com/msetina/pyhanko-eoi-plugin
Project-URL: Issue Tracker, https://github.com/msetina/pyhanko-eoi-plugin/issues
Keywords: signature,pdf,digital-signature,pkcs11
Classifier: Development Status :: 4 - Beta
Classifier: Intended Audience :: Information Technology
Classifier: Intended Audience :: Developers
Classifier: Operating System :: OS Independent
Classifier: License :: OSI Approved :: MIT License
Classifier: Programming Language :: Python :: 3.10
Classifier: Programming Language :: Python :: 3.11
Classifier: Programming Language :: Python :: 3.12
Classifier: Topic :: Security :: Cryptography
Classifier: Topic :: Software Development :: Libraries :: Python Modules
Requires-Python: >=3.10
License-File: LICENSE
Requires-Dist: pyHanko[pkcs11] >=0.23.0
Provides-Extra: mypy
Requires-Dist: pyhanko-eoi-plugin ; extra == 'mypy'
Requires-Dist: types-PyYAML ; extra == 'mypy'
Provides-Extra: testing
Requires-Dist: pyhanko-eoi-plugin ; extra == 'testing'
Requires-Dist: pytest >=6.1.1 ; extra == 'testing'
Requires-Dist: pytest-cov <4.2,>=4.0 ; extra == 'testing'
